package_exists/__init__.py
package_exists/package_exists.py
package_exists/pe_functions.py
package_exists/program.py
package_exists-0.1.3.dist-info/LICENSE
package_exists-0.1.3.dist-info/METADATA
package_exists-0.1.3.dist-info/WHEEL
package_exists-0.1.3.dist-info/top_level.txt
package_exists-0.1.3.dist-info/RECORD
