Metadata-Version: 2.1
Name: package-exists
Version: 0.1.3
Summary: Check whether a package name already exists or not in Pypi repository.
Home-page: https://pypi.org/project/package-exists/
Author: Daniel Diaz
Author-email: UNKNOWN
License: GNU GPLv3
Platform: UNKNOWN
